Metadata-Version: 1.1
Name: asmgen
Version: 2.1
Summary: 6502 code generator for Apple ][ and Atari 8-bit
Home-page: https://github.com/robmcmullen/asmgen
Author: Rob McMullen
Author-email: feedback@playermissile.com
License: GPL
Platform: UNKNOWN
Classifier: Programming Language :: Python :: 3.6
Classifier: Intended Audience :: Developers
Classifier: License :: OSI Approved :: GNU General Public License (GPL)
Classifier: Topic :: Software Development :: Libraries
Classifier: Topic :: Utilities
